complexifier/__init__.py
complexifier/main.py
complexifier/test_main.py
complexifier-1.0.0.dist-info/METADATA
complexifier-1.0.0.dist-info/WHEEL
complexifier-1.0.0.dist-info/licenses/LICENSE
complexifier-1.0.0.dist-info/RECORD
