Metadata-Version: 2.4
Name: complexifier
Version: 1.0.0
Summary: A library to make data worse
Project-URL: Homepage, https://github.com/ruyzambrano/complexifier
Project-URL: Issues, https://github.com/ruyzambrano/complexifier/issues
Author-email: Ruy Zambrano <ruyzambrano@gmail.com>
License-File: LICENSE
Classifier: License :: OSI Approved :: MIT License
Classifier: Operating System :: OS Independent
Classifier: Programming Language :: Python :: 3
Requires-Python: >=3.8
